primer/__init__.py
primer/circle.py
primer/config.py
primer/create_database.py
primer/database.py
primer/kmer.py
primer/logger.py
primer/main.py
primer/primer.py
primer/seq.py
primer/util.py
primertools-0.0.2.dist-info/METADATA
primertools-0.0.2.dist-info/WHEEL
primertools-0.0.2.dist-info/entry_points.txt
primertools-0.0.2.dist-info/top_level.txt
primertools-0.0.2.dist-info/RECORD
