Metadata-Version: 2.1
Name: primertools
Version: 0.0.2
Summary: A primer designer.
Home-page: https://github.com/dwpeng/primer
Author: dwpeng
Author-email: 1732889554@qq.com
License: UNKNOWN
Platform: UNKNOWN
Requires-Python: >=3.6
Requires-Dist: cbitmap
Requires-Dist: biopython
